<?xml version="1.0" encoding="UTF-8"?>
<sweep runs="1">
  <parameter constant_type="number" name="numberofGenomes" type="constant" value="1"/>
  <parameter constant_type="number" name="numberofHost" type="constant" value="2"/>
  <parameter constant_type="number" name="numberofRibosomes" type="constant" value="280"/>
  <parameter constant_type="number" name="numberofTF" type="constant" value="10"/>
  <parameter constant_type="number" name="distanceRadius" type="constant" value="2.1d"/>
  <parameter constant_type="number" name="distanceRadiusError" type="constant" value="0.2d"/>
  <parameter constant_type="number" name="distanceCapsid" type="constant" value="1.000000000001d"/>
  <parameter constant_type="number" name="distanceCapsidError" type="constant" value="0.2d"/>
  <parameter constant_type="boolean" name="ruleSeparation" type="constant" value="true"/>
  <parameter constant_type="boolean" name="ruleAlignment" type="constant" value="true"/>
  <parameter constant_type="boolean" name="ruleCohesion" type="constant" value="true"/>
  <parameter constant_type="number" name="distanceBind" type="constant" value="1.25d"/>
  <parameter constant_type="number" name="distanceBindError" type="constant" value="0.2d"/>
  <parameter constant_type="number" name="distanceVP1" type="constant" value="1.25d"/>
  <parameter constant_type="number" name="distanceVP1Error" type="constant" value="0.2d"/>
  <parameter constant_type="string" name="filePath" type="constant" value="/Users/svasa/repast2/assembly/logs"/>
  <parameter constant_type="number" name="cellRadius" type="constant" value="35"/>
  <parameter constant_type="number" name="nucleusRadius" type="constant" value="20"/>
  <parameter constant_type="number" name="numberofVP123" type="constant" value="0"/>
  <parameter constant_type="number" name="numberofVP1" type="constant" value="0"/>
  <parameter constant_type="number" name="numberofVP2" type="constant" value="0"/>
  <parameter constant_type="number" name="numberofVP3" type="constant" value="0"/>
  <parameter constant_type="boolean" name="viewCytoplasm" type="constant" value="true"/>
  <parameter constant_type="number" name="makeVLP"  type="constant" value="0.1d"/>
  <parameter constant_type="number" name="DNAPolDeath" type="constant" value="0.00005d"/>
  <parameter constant_type="number" name="transcribeEarly" type="constant" value="0.2d"/>
  <parameter constant_type="number" name="transcribeGenome" type="constant" value="0.001d"/>
  <parameter constant_type="number" name="transcribeLate" type="constant" value="0.002d"/>
  <parameter constant_type="number" name="transcribeDNAPol" type="constant" value="0.001d"/>
  <parameter constant_type="number" name="BKVEgress" type="constant" value="0.5d"/>
  <parameter constant_type="number" name="VLPEgress" type="constant" value="0.5d"/>
  <parameter constant_type="number" name="importTag" type="constant" value="0.4d"/>
  <parameter constant_type="number" name="importVP2" type="constant" value="0.8d"/>
  <parameter constant_type="number" name="importVP3" type="constant" value="0.8d"/>
  <parameter constant_type="number" name="tagDeath" type="constant" value="0.0001d"/>
  <parameter constant_type="number" name="spliceTag" type="constant" value="0.8d"/>
  <parameter constant_type="number" name="splicetag" type="constant" value="0.2d"/>
  <parameter constant_type="number" name="spliceVP1" type="constant" value="0.7d"/>
  <parameter constant_type="number" name="spliceVP23" type="constant" value="0.2d"/>
  <parameter constant_type="number" name="exportmRNA" type="constant" value="0.4d"/>
  <parameter constant_type="number" name="translation" type="constant" value="0.4d"/>
  <parameter constant_type="number" name="VLPDeath" type="constant" value="0.001d"/>
  <parameter constant_type="number" name="mRNADeath" type="constant" value="0.0001d"/>
</sweep>